Metadata-Version: 1.0
Name: gouqi
Version: 1.0.0
Summary: a function to input this datas
Home-page: https://github.com/GMZ-426/Python_code
Author: GMZ-426
Author-email: 1847394932@qq.com
License: UNKNOWN
Platform: UNKNOWN
